app1/__init__.py
app1/admin.py
app1/apps.py
app1/forms.py
app1/models.py
app1/tests.py
app1/urls.py
app1/views.py
app1/migrations/0001_initial.py
app1/migrations/0002_contact_message.py
app1/migrations/__init__.py
django_contactus_email1-2.1.dist-info/LICENSE
django_contactus_email1-2.1.dist-info/METADATA
django_contactus_email1-2.1.dist-info/WHEEL
django_contactus_email1-2.1.dist-info/top_level.txt
django_contactus_email1-2.1.dist-info/RECORD
