Metadata-Version: 2.1
Name: django-contactus-email1
Version: 2.1
Summary: A Django app.
Home-page: https://github.com/Ajayakarki/DailyTask/tree/master/Django
Author: Ajaya
Author-email: ajaya.carkey890@gmail.com
Maintainer: Asbin
Maintainer-email: asbin@gmail.com
License: MIT  # Example license
Keywords: django demo
Classifier: Environment :: Web Environment
Classifier: Framework :: Django
Classifier: Intended Audience :: Developers
Classifier: License :: OSI Approved :: MIT License
Classifier: Operating System :: OS Independent
Classifier: Programming Language :: Python
Classifier: Programming Language :: Python :: 3
Classifier: Programming Language :: Python :: 3 :: Only
Classifier: Programming Language :: Python :: 3.8
Classifier: Programming Language :: Python :: 3.9
Classifier: Topic :: Software Development :: Libraries :: Python Modules
Classifier: Topic :: Internet :: WWW/HTTP :: Dynamic Content
Requires-Python: >=3.8
License-File: LICENSE
